README.md
setup.py
FlaskCerberus/__init__.py
FlaskCerberus.egg-info/PKG-INFO
FlaskCerberus.egg-info/SOURCES.txt
FlaskCerberus.egg-info/dependency_links.txt
FlaskCerberus.egg-info/not-zip-safe
FlaskCerberus.egg-info/requires.txt
FlaskCerberus.egg-info/top_level.txt