Metadata-Version: 1.1
Name: FlaskCerberus
Version: 0.1rc1
Summary: Add Cerberus validation to Flask
Home-page: http://github.com/atlanteanio/FlaskCerberus/
Author: Dan Sikes
Author-email: dsikes@atlantean.io
License: UNKNOWN
Platform: any
Classifier: Environment :: Web Environment
Classifier: Intended Audience :: Developers
Classifier: License :: OSI Approved :: BSD License
Classifier: Operating System :: OS Independent
Classifier: Programming Language :: Python
Classifier: Topic :: Internet :: WWW/HTTP :: Dynamic Content
Classifier: Topic :: Software Development :: Libraries :: Python Modules
